{
  "status": "廢止",
  "name": "臺灣地區平均地權土地債券發行條例",
  "revision": [
    {
      "date": "1956.6.1",
      "content": {
        "1": {
          "num": 1,
          "zh": "第一條",
          "article": "中央政府為在臺灣省實施都市平均地權，授權臺灣省政府依本條例之規定，發行臺灣省實施都市平均地權土地債券（以下簡稱本債券）。本債券專作，依照實施都市平均地權條例施行照價收買時，補償土地或建築改良物價款之用。"
        },
        "2": {
          "num": 2,
          "zh": "第二條",
          "article": "本債券之發行及還本付息事務，由臺灣省政府委託臺灣土地銀行辦理。"
        },
        "3": {
          "num": 3,
          "zh": "第三條",
          "article": "本債券定額為新臺幣一億五千萬元，自中華民國四十五年八月二十五日開始按照票面額十足發行，其票面額分為新臺幣一萬元、五千元、一千元、五百元、一百元五種。"
        },
        "4": {
          "num": 4,
          "zh": "第四條",
          "article": "本債券以左列各款收入為擔保，並由省庫保證之：一、依照實施都市平均地權條例施行照價收買之土地及建築改良物出租後之租金及違約金收入。二、依照實施都市平均地權條例施行照價收買之土地及建築改良物出售後之價款收入。前項各款收入應設置臺灣省實施都市平均地權土地償券還本付息保證基金專戶，存儲臺灣土地銀行，以備兌付到期本息，如有不足，由省政府指撥專款墊付之。"
        },
        "5": {
          "num": 5,
          "zh": "第五條",
          "article": "本債券採無記名式，憑券兌付不得掛失。"
        },
        "6": {
          "num": 6,
          "zh": "第六條",
          "article": "本債券利率定為年息百分之四。"
        },
        "7": {
          "num": 7,
          "zh": "第七條",
          "article": "本債券之償還採本息合計均等攤還法，自發行之次年起，每年攤還一次，分五年償清，其還本付息表應由主管機關每年按實際發行數額計算公告之。"
        },
        "8": {
          "num": 8,
          "zh": "第八條",
          "article": "本債券每年還本付息日期，定為八月二十五日。"
        },
        "9": {
          "num": 9,
          "zh": "第九條",
          "article": "本債券得轉讓買賣及充司法上、稅務上與其他公務上之保證，其各年本息券除得抵繳各該年承租被照價買土地之租金外，並得十足用以承購政府出售照價收買之土地。"
        },
        "10": {
          "num": 10,
          "zh": "第十條",
          "article": "本債券免予課徵印花稅所得稅及特別稅課之戶稅。"
        },
        "11": {
          "num": 11,
          "zh": "第十一條",
          "article": "對於本債券如有偽造或變造之行為者，依法懲治。"
        },
        "12": {
          "num": 12,
          "zh": "第十二條",
          "article": "本條例自公布日施行。"
        }
      }
    },
    {
      "date": "1969.1.28",
      "content": {
        "1": {
          "num": 1,
          "zh": "第一條",
          "article": "中央政府為在臺灣地區實施都市平均地權，授權臺灣省政府及臺北市政府，依本條例之規定，發行各該省、市實施都市平均地權土地債券（以下簡稱本債券）。本債券專作依照實施都市平均地權條例施行照價收買、區段徵收及超額土地徵收時，補償土地或建築改良物價款之用。"
        },
        "2": {
          "num": 2,
          "zh": "第二條",
          "article": "本債券於償付價款時，依實施都市平均地權條例第五條之規定，按成搭發。"
        },
        "3": {
          "num": 3,
          "zh": "第三條",
          "article": "本債券之發行及還本付息事務，由發行之省、市政府委託臺灣土地銀行辦理。"
        },
        "4": {
          "num": 4,
          "zh": "第四條",
          "article": "本債券每年發行一次，其發行數額、日期、債券面額及利率，由發行之省、市政府報請行政院核定之。"
        },
        "5": {
          "num": 5,
          "zh": "第五條",
          "article": "本債券以左列各款收入為擔保，並由省、市庫保證之：一、依照實施都市平均地權條例，施行照價收買、區段徵收及超額土地徵收之土地及建築改良物，出租後之租金及違約金收入。二、依照實施都市平均地權條例，施行照價收買、區段徵收及超額土地徵收之土地及建築改良物，出售後之價款收入。前項各款收入，應設置臺灣省或臺北市實施都市平均地權土地債券還本付息保證基金，專戶存儲臺灣土地銀行，以備到期還本付息；如有不足，由發行之省、市政府指撥專款墊付之。"
        },
        "6": {
          "num": 6,
          "zh": "第六條",
          "article": "臺灣省各縣（市），辦理照價收買、區段徵收及超額土地徵收，由省撥借土地債券，分年歸還；其償還辦法及財源，由省政府定之。"
        },
        "7": {
          "num": 7,
          "zh": "第七條",
          "article": "本債券採無記名式，憑券兌付，其遺失被盜或滅失者，不得掛失止付，並不適用民法第七百二十條第一項但書、第七百二十五條及第七百二十七條之規定。"
        },
        "8": {
          "num": 8,
          "zh": "第八條",
          "article": "本債券之償還，依本息合計均等攤還法，自發行之日起，每屆滿一年，攤還本息一次，分五年償清；其還本付息表應由發行之省、市政府按年公告之。"
        },
        "9": {
          "num": 9,
          "zh": "第九條",
          "article": "本債券得轉讓、買賣，及充司法上、稅務上與其他公務上之保證。"
        },
        "10": {
          "num": 10,
          "zh": "第十條",
          "article": "本債券當年本息券，得十足用以承購當年出售之照價收買、區段徵收及超額土地徵收之土地，並得抵繳承租上列土地當年之租金。"
        },
        "11": {
          "num": 11,
          "zh": "第十一條",
          "article": "本債券免予課徵印花稅及所得稅。"
        },
        "12": {
          "num": 12,
          "zh": "第十二條",
          "article": "對於本債券如有偽造或變造之行為者，依法懲治。"
        },
        "13": {
          "num": 13,
          "zh": "第十三條",
          "article": "本條例自公布日施行。"
        }
      }
    },
    {
      "date": "1978.1.13",
      "content": {
        "1": {
          "num": 1,
          "zh": "第一條",
          "article": "中央政府為在臺灣地區實施平均地權，授權臺灣省政府及臺北市政府依本條例之規定，發行各該省、市平均地權土地債券（以下簡稱本債券）。"
        },
        "2": {
          "num": 2,
          "zh": "第二條",
          "article": "本債券專作依照平均地權條例實施照價收買、區段徵收時，補償土地價款之用。本債券於償付前項土地價款時，依平均地權條例第六條之規定，按成搭發。"
        },
        "3": {
          "num": 3,
          "zh": "第三條",
          "article": "本債券之發行及還本付息事務，由發行之省（市）政府委託臺灣土地銀行或臺北市銀行辦理。"
        },
        "4": {
          "num": 4,
          "zh": "第四條",
          "article": "本債券發行數額、日期、債券面額及利率，由發行之省（市）政府報請行政院核定之。"
        },
        "5": {
          "num": 5,
          "zh": "第五條",
          "article": "本債券由省（市）庫保證，並以省（市）平均地權基金為還本付息之財源。"
        },
        "6": {
          "num": 6,
          "zh": "第六條",
          "article": "臺灣省各縣（市）辦理照價收買、區段徵收，由省撥借土地債券，分年歸還；其償還暨收支管理辦法由省政府定之。"
        },
        "7": {
          "num": 7,
          "zh": "第七條",
          "article": "本債券採無記名式，憑券兌付，其遺失、被盜或滅失者，不得掛失止付，並不適用民法第七百二十條第一項但書、第七百二十五條及第七百二十七條之規定。"
        },
        "8": {
          "num": 8,
          "zh": "第八條",
          "article": "本債券之償還，依本息合計均等攤還法，自發行之日起，每屆滿一年，攤還本息一次，分五年償清；其還本付息表應由發行之省（市）政府按年公告之。"
        },
        "9": {
          "num": 9,
          "zh": "第九條",
          "article": "本債券得轉讓、買賣，及充司法上、稅務上與其他公務上之保證。"
        },
        "10": {
          "num": 10,
          "zh": "第十條",
          "article": "本債券當年本息券持有人，得十足用以承購當年政府出售之照價收買、區段徵收之土地，並得抵繳承租上列土地當年之租金。"
        },
        "11": {
          "num": 11,
          "zh": "第十一條",
          "article": "本債券免徵印花稅及所得稅。"
        },
        "12": {
          "num": 12,
          "zh": "第十二條",
          "article": "本債券自最後一次還本付息開付日所屬會計年度終了後，屆滿五年仍未請領者，不再兌付。"
        },
        "13": {
          "num": 13,
          "zh": "第十三條",
          "article": "本條例自公布日施行。"
        }
      }
    },
    {
      "date": "1981.7.3",
      "content": {
        "1": {
          "num": 1,
          "zh": "第一條",
          "article": "中央政府為在臺灣地區實施平均地權，授權該區省（市）政府依平均地權條例第五條之規定，發行各該省（市）平均地權土地債券（以下簡稱本債券），特制定本條例。",
          "reason": "為適應高雄市之改制、配合其推行平均地權政策之需要，暨為標明本條例之立法依據，爰為修訂。"
        },
        "3": {
          "num": 3,
          "zh": "第三條",
          "article": "本債券之發行及還本付息事務，由發行之省（市）政府分別委託臺灣土地銀行或直轄市市銀行辦理。",
          "reason": "為因應高雄市之實際需要，爰比照臺灣地區公共建設土地債券發行條例第六條規定之成例，將「或臺北市銀行」修訂為「或直轄市市銀行」為受託辦理本債券之發行及還本付息機構。"
        }
      }
    }
  ]
}