{
  "status": "停止適用",
  "name": "上海市市政公債條例",
  "revision": [
    {
      "date": "1929.8.24",
      "content": {
        "1": {
          "num": 1,
          "zh": "第一條",
          "article": "本公債定名為上海特別市市政公債。"
        },
        "2": {
          "num": 2,
          "zh": "第二條",
          "article": "本公債定額為三百萬元。"
        },
        "3": {
          "num": 3,
          "zh": "第三條",
          "article": "本公債專充辦理左列市政事業之用：一、建築幹道。二、建築市中心區域。三、創辦市立銀行。四、整理舊公債。"
        },
        "4": {
          "num": 4,
          "zh": "第四條",
          "article": "本公債定為年息八厘。"
        },
        "5": {
          "num": 5,
          "zh": "第五條",
          "article": "本公債按照票面九八發行，即每票面百元實收國幣九十八元。"
        },
        "6": {
          "num": 6,
          "zh": "第六條",
          "article": "本公債定於中華民國十八年十月一日發行。"
        },
        "7": {
          "num": 7,
          "zh": "第七條",
          "article": "本公債自民國十九年起至民國二十六年止，以每年三月三十一日及九月三十日為付息之期。"
        },
        "8": {
          "num": 8,
          "zh": "第八條",
          "article": "本公債自民國二十年三月三十一日起至民國二十六年九月三十日止，分十四期每六個月抽籤還本一次，前十二期每期還本二十萬元，最後兩期每期還本三十萬元。"
        },
        "9": {
          "num": 9,
          "zh": "第九條",
          "article": "本公債以本特別市房捐收入為擔保，每月依照還本付息表所載數目，儘先提存指定銀行為償還本息之基金。關於基金之保管組織，基金保管委員會辦理，其保管條例另訂之。"
        },
        "10": {
          "num": 10,
          "zh": "第十條",
          "article": "本公債票面定為五百圓、百圓、十圓、五圓四種，概為無記名式。"
        },
        "11": {
          "num": 11,
          "zh": "第十一條",
          "article": "本公債票得由持票人隨意買賣抵押，並得充本特別市公務上之保證金或擔保品，及本特別市公共團體機關之基金或準備金，其到期本息票得為繳納本特別市捐稅之用。"
        },
        "12": {
          "num": 12,
          "zh": "第十二條",
          "article": "本公債還本付息，由基金保管委員會指定銀行委託經理之。"
        },
        "13": {
          "num": 13,
          "zh": "第十三條",
          "article": "本公債每屆抽籤之期，由審計院本特別市政府及基金保管委員會派員監視，並任人參觀。"
        },
        "14": {
          "num": 14,
          "zh": "第十四條",
          "article": "對於本公債如有毀損信用或偽造之行為者，依法懲治。"
        },
        "15": {
          "num": 15,
          "zh": "第十五條",
          "article": "本公債發行細則另定之。"
        },
        "16": {
          "num": 16,
          "zh": "第十六條",
          "article": "本條例自公布日施行。"
        }
      }
    },
    {
      "date": "1931.3.21",
      "content": {
        "1": {
          "num": 1,
          "zh": "第一條",
          "article": "本公債定名為上海市市政公債。"
        },
        "2": {
          "num": 2,
          "zh": "第二條",
          "article": "本公債定額為三百萬元。"
        },
        "3": {
          "num": 3,
          "zh": "第三條",
          "article": "本公債專充辦理左列市政事業之用：一、建築幹道。二、建築市中心區域。三、創辦市立銀行。四、整理舊公債。"
        },
        "4": {
          "num": 4,
          "zh": "第四條",
          "article": "本公債定為年息八厘。"
        },
        "5": {
          "num": 5,
          "zh": "第五條",
          "article": "本公債按照票面九八發行，即每票面百元實收國幣九十八元。"
        },
        "6": {
          "num": 6,
          "zh": "第六條",
          "article": "本公債定於中華民國十八年十月一日發行。"
        },
        "7": {
          "num": 7,
          "zh": "第七條",
          "article": "本公債自民國十九年起至民國二十六年止以每年三月三十一日及九月三十日為付息之期。"
        },
        "8": {
          "num": 8,
          "zh": "第八條",
          "article": "本公債自民國二十年三月三十一日起至民國二十六年九月三十日止，分十四期每六個月抽籤還本一次，前十二期每期還本二十一萬元，最後兩期還本二十四萬元。"
        },
        "9": {
          "num": 9,
          "zh": "第九條",
          "article": "本公債以本市房捐收入為擔保，每月依照還本付息表所載數目，盡先提存指定銀行為償還本息之基金。關於基金之保管組織基金委員會辦理，其保管條例另定之。"
        },
        "10": {
          "num": 10,
          "zh": "第十條",
          "article": "本公債票面定為五百元、百元、十元、五元四種，概為無記名式。"
        },
        "11": {
          "num": 11,
          "zh": "第十一條",
          "article": "本公債票得由持票人隨意買賣抵押，並得充本市公務上之保證金，或擔保品，及本市公共團體機關之基金或準備金，其到期本息票，得為繳納本市捐稅之用。"
        },
        "12": {
          "num": 12,
          "zh": "第十二條",
          "article": "本公債還本付息由基金保管委員會指定銀行委託經理之。"
        },
        "13": {
          "num": 13,
          "zh": "第十三條",
          "article": "本公債每屆抽籤之期，由審計部、本市政府及基金保管委員會派員監視，並任人參觀。"
        },
        "14": {
          "num": 14,
          "zh": "第十四條",
          "article": "對於本公債如有毀損信用或偽造之行為者，依法懲治。"
        },
        "15": {
          "num": 15,
          "zh": "第十五條",
          "article": "本公債發行細則另定之。"
        },
        "16": {
          "num": 16,
          "zh": "第十六條",
          "article": "本條例自公布日施行。"
        }
      }
    }
  ]
}