{
  "1971.12.14": [
    {
      "link": "http://lis.ly.gov.tw/ttscgi/lgimg?@6048960001;0005;0005",
      "desc": "60卷96期449號 5~5頁",
      "progress": "一讀",
      "committee": "法制 教育"
    }
  ],
  "1972.01.08": [
    {
      "link": "http://lis.ly.gov.tw/ttscgi/lgimg?@6149270002;0014;0015",
      "desc": "61卷27期480號 14~15頁",
      "progress": "委員會審查",
      "committee": "法制 教育"
    }
  ],
  "1972.03.07": [
    {
      "link": "http://lis.ly.gov.tw/ttscgi/lgimg?@6149190001;0038;0039",
      "desc": "61卷19期472號 38~39頁",
      "progress": "三讀",
      "committee": "法制 教育"
    }
  ],
  "1973.01.16": [
    {
      "link": "http://lis.ly.gov.tw/ttscgi/lgimg?@6250040001;0003;0003",
      "desc": "62卷4期560號 3~3頁",
      "progress": "一讀",
      "committee": "法制 教育"
    }
  ],
  "1973.03.12": [
    {
      "link": "http://lis.ly.gov.tw/ttscgi/lgimg?@6251350002;0025;0027",
      "desc": "62卷35期591號 25~27頁",
      "progress": "委員會審查",
      "committee": "法制 教育"
    }
  ],
  "1973.03.27": [
    {
      "link": "http://lis.ly.gov.tw/ttscgi/lgimg?@6251220001;0005;0006",
      "desc": "62卷22期578號 5~6頁",
      "progress": "三讀",
      "committee": "法制 教育"
    }
  ]
}